blackjack/__init__.py
blackjack/dealer.py
blackjack/game.py
blackjack/game_utils.py
blackjack/main.py
blackjack/new_card.py
blackjack/new_trump.py
blackjack/player.py
blackjack/userstats.py
blackjack/gui/__init__.py
blackjack/gui/game_page.py
blackjack/gui/init_page.py
blackjack/gui/login_page.py
blackjack/gui/menu_page.py
21blackjack_gui-1.0.0.dist-info/LICENCE.md
21blackjack_gui-1.0.0.dist-info/METADATA
21blackjack_gui-1.0.0.dist-info/WHEEL
21blackjack_gui-1.0.0.dist-info/entry_points.txt
21blackjack_gui-1.0.0.dist-info/top_level.txt
21blackjack_gui-1.0.0.dist-info/RECORD
