Metadata-Version: 2.1
Name: 21blackjack-gui
Version: 1.0.0
Summary: A python-based blackjack game with a GUI built in tkinter.
Home-page: https://github.com/outlawF16/blackjack
Author: Faizan Ahmed
Classifier: Programming Language :: Python :: 3
Classifier: License :: OSI Approved :: MIT License
Classifier: Operating System :: OS Independent
Requires-Python: >=3.6
License-File: LICENCE.md
